tgcalls.cp37-win32.pyd
tgcalls.pdb
tgcalls-2.0.0.dist-info/LICENSE
tgcalls-2.0.0.dist-info/METADATA
tgcalls-2.0.0.dist-info/WHEEL
tgcalls-2.0.0.dist-info/top_level.txt
tgcalls-2.0.0.dist-info/RECORD
