Metadata-Version: 2.1
Name: tgcalls
Version: 2.0.0
Summary: a Python binding for tgcalls C++ library
Home-page: https://github.com/MarshalX/tgcalls
Author: Il`ya Semyonov
Author-email: ilya@marshal.dev
License: LGPLv3
Project-URL: Telegram Channel, https://t.me/tgcallslib
Project-URL: Telegram Chat, https://t.me/tgcallschat
Project-URL: Author, https://github.com/MarshalX
Keywords: python,library,telegram,async,asynchronous,webrtc,lib,voice-chat,voip,group-chat,video-call,calls,pyrogram,telethon,pytgcalls,tgcalls
Platform: UNKNOWN
Classifier: Development Status :: 5 - Production/Stable
Classifier: Natural Language :: English
Classifier: Intended Audience :: Developers
Classifier: License :: OSI Approved :: GNU Lesser General Public License v3 (LGPLv3)
Classifier: Operating System :: OS Independent
Classifier: Operating System :: MacOS
Classifier: Operating System :: Unix
Classifier: Topic :: Internet
Classifier: Topic :: Multimedia
Classifier: Topic :: Multimedia :: Video
Classifier: Topic :: Multimedia :: Video :: Capture
Classifier: Topic :: Multimedia :: Sound/Audio
Classifier: Topic :: Multimedia :: Sound/Audio :: Capture/Recording
Classifier: Topic :: Communications
Classifier: Topic :: Communications :: Internet Phone
Classifier: Topic :: Communications :: Telephony
Classifier: Topic :: Software Development :: Libraries
Classifier: Topic :: Software Development :: Libraries :: Python Modules
Classifier: Programming Language :: C++
Classifier: Programming Language :: Python
Classifier: Programming Language :: Python :: 3
Classifier: Programming Language :: Python :: 3 :: Only
Classifier: Programming Language :: Python :: 3.6
Classifier: Programming Language :: Python :: 3.7
Classifier: Programming Language :: Python :: 3.8
Classifier: Programming Language :: Python :: 3.9
Classifier: Programming Language :: Python :: Implementation
Classifier: Programming Language :: Python :: Implementation :: CPython
Requires-Python: ~=3.6
License-File: LICENSE
